{
    "patches": [
        {
            "label": "2026-05-05_18-19-59",
            "content": "package main\n\nimport (\n\t\"bufio\"\n\t\"fmt\"\n\t\"os\"\n\t\"strings\"\n)\n\n\nfunc main() {\n\tscanner := bufio.NewScanner(os.Stdin)\n// \tll := NewLList()\n\n\tfor {\n\t\tfmt.Print(\"$\")\n\t\tif !scanner.Scan() {\n\t\t\tbreak\n\t\t}\n\t\tline := scanner.Text()\n\t\tfmt.Println(line)\n\t\targs := strings.Fields(line)\n\n\t\tif len(args) == 0 {\n\t\t\tcontinue\n\t\t}\n\n\t\tcmd := args[0]\n\n\t\tswitch cmd {\n\t\tcase \"show\":\n\t\t\t// fmt.Println(ll.String())\n\t\tcase \"size\":\n\t\t\t// fmt.Println(ll.Size())\n\t\tcase \"push_back\":\n\t\t\t// for _, v := range args[1:] {\n\t\t\t// \tnum, _ := strconv.Atoi(v)\n\t\t\t// \tll.PushBack(num)\n\t\t\t// }\n\t\tcase \"push_front\":\n\t\t\t// for _, v := range args[1:] {\n\t\t\t// \tnum, _ := strconv.Atoi(v)\n\t\t\t// \tll.PushFront(num)\n\t\t\t// }\n\t\tcase \"pop_back\":\n\t\t\t// ll.PopBack()\n\t\tcase \"pop_front\":\n\t\t\t// ll.PopFront()\n\t\tcase \"clear\":\n\t\t\t// ll.Clear()\n\t\tcase \"end\":\n\t\t\treturn\n\t\tdefault:\n\t\t\tfmt.Println(\"fail: comando invalido\")\n\t\t}\n\t}\n}\n",
            "lines": "57"
        }
    ]
}